sciope/__init__.py
sciope/core/__init__.py
sciope/core/core.py
sciope/data/__init__.py
sciope/data/dataset.py
sciope/designs/__init__.py
sciope/designs/factorial_design.py
sciope/designs/initial_design_base.py
sciope/designs/latin_hypercube_sampling.py
sciope/designs/random_sampling.py
sciope/features/__init__.py
sciope/features/feature_extraction.py
sciope/inference/__init__.py
sciope/inference/abc_inference.py
sciope/inference/bnn_inference.py
sciope/inference/inference_base.py
sciope/inference/rep_smc_abc.py
sciope/inference/smc_abc.py
sciope/models/__init__.py
sciope/models/ann_regressor.py
sciope/models/bnn_classifier.py
sciope/models/cnn_regressor.py
sciope/models/dnn_base.py
sciope/models/dnn_regressor.py
sciope/models/gp_regressor.py
sciope/models/label_propagation.py
sciope/models/model_base.py
sciope/models/pen_regressor.py
sciope/models/svm_regressor.py
sciope/sampling/__init__.py
sciope/sampling/maximin_sampling.py
sciope/sampling/sampling_base.py
sciope/stochmet/__init__.py
sciope/stochmet/stochmet.py
sciope/utilities/__init__.py
sciope/utilities/distancefunctions/__init__.py
sciope/utilities/distancefunctions/distance_base.py
sciope/utilities/distancefunctions/euclidean.py
sciope/utilities/distancefunctions/manhattan.py
sciope/utilities/distancefunctions/naive_squared.py
sciope/utilities/epsilonselectors/__init__.py
sciope/utilities/epsilonselectors/absolute_epsilon_selector.py
sciope/utilities/epsilonselectors/epsilon_selector.py
sciope/utilities/epsilonselectors/relative_epsilon_selector.py
sciope/utilities/gillespy2/__init__.py
sciope/utilities/gillespy2/wrapper.py
sciope/utilities/housekeeping/__init__.py
sciope/utilities/housekeeping/sciope_logger.py
sciope/utilities/housekeeping/sciope_profiler.py
sciope/utilities/perturbationkernels/__init__.py
sciope/utilities/perturbationkernels/kernel_base.py
sciope/utilities/perturbationkernels/multivariate_normal.py
sciope/utilities/priors/__init__.py
sciope/utilities/priors/prior_base.py
sciope-0.4.dist-info/LICENSE.txt
sciope-0.4.dist-info/METADATA
sciope-0.4.dist-info/WHEEL
sciope-0.4.dist-info/top_level.txt
sciope-0.4.dist-info/RECORD
