Metadata-Version: 2.1
Name: sciope
Version: 0.4
Summary: The sciope toolbox for surrogate modeling, likelihood-free parameter inference and black-box optimization.
Home-page: https://github.com/sciope/sciope
Author: Prashant Singh; Fredrik Wrede; Andreas Hellander
Author-email: prashant.singh@it.uu.se
License: Apache 2.0
Keywords: parameter inference surrogate modeling optimization sweeps sampling design model reduction
Platform: UNKNOWN
Classifier: Development Status :: 3 - Alpha
Classifier: Intended Audience :: Science/Research
Classifier: Topic :: Scientific/Engineering
Classifier: License :: OSI Approved :: Apache Software License
Classifier: Programming Language :: Python :: 3
Classifier: Programming Language :: Python :: 3.5
Requires-Dist: numpy (>=1.16.5)
Requires-Dist: scipy
Requires-Dist: scikit-learn
Requires-Dist: gillespy2
Requires-Dist: tsfresh (==0.15.0)
Requires-Dist: ipywidgets
Requires-Dist: dask
Requires-Dist: distributed
Requires-Dist: matplotlib
Requires-Dist: umap-learn
Provides-Extra: dev
Requires-Dist: check-manifest ; extra == 'dev'
Provides-Extra: test
Requires-Dist: coverage ; extra == 'test'
